regex_field/__init__.py
regex_field/apps.py
regex_field/fields.py
regex_field/urls.py
regex_field/version.py
regex_field/docs/release_notes.rst
regex_field/tests/__init__.py
regex_field/tests/models.py
regex_field/tests/regex_field_tests.py
regex_field/tests/fixtures/data.json
django_regex_field-3.1.0.dist-info/LICENSE
django_regex_field-3.1.0.dist-info/METADATA
django_regex_field-3.1.0.dist-info/WHEEL
django_regex_field-3.1.0.dist-info/top_level.txt
django_regex_field-3.1.0.dist-info/RECORD
