Metadata-Version: 2.1
Name: django-regex-field
Version: 3.1.0
Summary: Django Regex Field
Home-page: https://github.com/ambitioninc/django-regex-field
Author: Wes Kendall
Author-email: opensource@ambition.com
License: MIT
Keywords: Django,Regex Field
Classifier: Programming Language :: Python
Classifier: Programming Language :: Python :: 3.7
Classifier: Programming Language :: Python :: 3.8
Classifier: Programming Language :: Python :: 3.9
Classifier: Intended Audience :: Developers
Classifier: License :: OSI Approved :: MIT License
Classifier: Operating System :: OS Independent
Classifier: Framework :: Django
Classifier: Framework :: Django :: 2.2
Classifier: Framework :: Django :: 3.0
Classifier: Framework :: Django :: 3.1
Classifier: Framework :: Django :: 3.2
Classifier: Framework :: Django :: 4.0
Classifier: Framework :: Django :: 4.1
License-File: LICENSE
Requires-Dist: Django (>=3.2)
